setup.py
credits/__init__.py
credits/address.py
credits/digest.py
credits/hash.py
credits/interface.py
credits/key.py
credits/proof.py
credits/test.py
credits/transaction.py
credits/transform.py
credits.common.egg-info/PKG-INFO
credits.common.egg-info/SOURCES.txt
credits.common.egg-info/dependency_links.txt
credits.common.egg-info/namespace_packages.txt
credits.common.egg-info/requires.txt
credits.common.egg-info/top_level.txt