Metadata-Version: 1.1
Name: credits.common
Version: 3.0.0
Summary: Credits blockchain framework common client library
Home-page: https://github.com/CryptoCredits/credits-common
Author: Credits Developers
Author-email: admin@credits.vision
License: UNKNOWN
Download-URL: https://github.com/CryptoCredits/credits-common/tarball/3.0.0
Platform: UNKNOWN
